javabridge/__init__.py
javabridge/_javabridge.cpython-39-darwin.so
javabridge/jutil.py
javabridge/locate.py
javabridge/noseplugin.py
javabridge/wrappers.py
javabridge/jars/cpython.jar
javabridge/jars/libjava2cpython.jnilib
javabridge/jars/rhino-1.7R4.jar
javabridge/jars/runnablequeue.jar
javabridge/jars/test.jar
javabridge/tests/__init__.py
javabridge/tests/test_cpython.py
javabridge/tests/test_javabridge.py
javabridge/tests/test_jutil.py
javabridge/tests/test_wrappers.py
python_javabridge-4.0.3.dist-info/LICENSE
python_javabridge-4.0.3.dist-info/METADATA
python_javabridge-4.0.3.dist-info/WHEEL
python_javabridge-4.0.3.dist-info/entry_points.txt
python_javabridge-4.0.3.dist-info/top_level.txt
python_javabridge-4.0.3.dist-info/RECORD
