Metadata-Version: 2.1
Name: python-javabridge
Version: 4.0.3
Summary: Python wrapper for the Java Native Interface
Home-page: http://github.com/CellProfiler/python-javabridge/
License: BSD License
Classifier: Development Status :: 5 - Production/Stable
Classifier: License :: OSI Approved :: BSD License
Classifier: Programming Language :: Java
Classifier: Programming Language :: Python :: 2
Classifier: Programming Language :: Python :: 3
License-File: LICENSE
Requires-Dist: numpy >=1.20.1
